parchments/__init__.py
parchments/core/__init__.py
parchments/core/block.py
parchments/core/choices.py
parchments/core/core.py
parchments/core/data.py
parchments/core/debug.py
parchments/core/grid.py
parchments/core/period.py
parchments/core/row.py
parchments/core/validation.py
parchments/core/value.py
parchments/test/__init__.py
parchments/test/test_grid.py
parchments/test/test_math.py
parchments/test/test_median.py
parchments/test/test_period.py
parchments/test/test_project.py
parchments-0.1.4.dist-info/LICENSE
parchments-0.1.4.dist-info/METADATA
parchments-0.1.4.dist-info/WHEEL
parchments-0.1.4.dist-info/top_level.txt
parchments-0.1.4.dist-info/RECORD
