Metadata-Version: 2.1
Name: parchments
Version: 0.1.4
Summary: A grid based financial analysis tool for generating easy to use dictionary objects.
Home-page: https://github.com/idlelosthobo/parchments
Author: Nathan Johnson
Author-email: drugen@gmail.com
License: UNKNOWN
Platform: UNKNOWN
Classifier: Programming Language :: Python :: 3
Classifier: License :: OSI Approved :: MIT License
Classifier: Operating System :: OS Independent
Requires-Python: >=3.6
